{
    "$schema": "https://raw.githubusercontent.com/ScoopInstaller/Scoop/master/schema.json",
    "version": "0.74.1",
    "description": "A general-purpose command-line fuzzy finder.",
    "homepage": "https://github.com/junegunn/fzf",
    "license": {
        "identifier": "MIT",
        "url": "https://github.com/junegunn/fzf/blob/master/LICENSE"
    },
    "architecture": {
        "64bit": {
            "url": "https://github.com/junegunn/fzf/releases/download/v0.74.1/fzf-0.74.1-windows_amd64.zip",
            "hash": "d83a94a68a9203f6366754123c0e4d7a61e16be18a5d845f4838664b330c4f5f"
        }
    },
    "bin": "fzf.exe",
    "checkver": "github",
    "autoupdate": {
        "architecture": {
            "64bit": {
                "url": "https://github.com/junegunn/fzf/releases/download/v$version/fzf-$version-windows_amd64.zip",
                "hash": {
                    "url": "$baseurl/fzf_$version_checksums.txt"
                }
            }
        }
    }
}
