{
    "$schema": "https://raw.githubusercontent.com/ScoopInstaller/Scoop/master/schema.json",
    "version": "1.29.4",
    "description": "An HTTP web server, reverse proxy, content cache, load balancer, TCP/UDP proxy server, and mail proxy server.",
    "homepage": "https://nginx.org/",
    "license": {
        "identifier": "BSD-2-Clause",
        "url": "https://nginx.org/LICENSE"
    },
    "url": "https://github.com/nginx/nginx/releases/download/release-1.29.4/nginx-1.29.4.zip",
    "hash": "658336377f103cb5908085d9ff31b48a7b43311403d2a0779a935ddc3caefab3",
    "extract_dir": "nginx-1.29.4",
    "bin": [
        [
            "nginx.exe",
            "nginx",
            "-p",
            "\"$dir\""
        ]
    ],
    "persist": [
        "conf",
        "html",
        "logs",
        "temp"
    ],
    "checkver": {
        "github": "https://github.com/nginx/nginx",
        "regex": "release-([\\d.]+)"
    },
    "autoupdate": {
        "url": "https://github.com/nginx/nginx/releases/download/release-$version/nginx-$version.zip",
        "extract_dir": "nginx-$version"
    }
}
